shakecast/__init__.py
shakecast/__main__.py
shakecast/api.py
shakecast/test_env.py
shakecast/ui.py
shakecast/version
shakecast/app/__init__.py
shakecast/app/env.py
shakecast/app/eventprocessing.py
shakecast/app/functions.py
shakecast/app/grid.py
shakecast/app/impact.py
shakecast/app/inventory.py
shakecast/app/jsonencoders.py
shakecast/app/newthread.py
shakecast/app/productdownload.py
shakecast/app/productgeneration.py
shakecast/app/sc_logging.py
shakecast/app/server.py
shakecast/app/servertestfunctions.py
shakecast/app/startup.py
shakecast/app/task.py
shakecast/app/templates.py
shakecast/app/urlopener.py
shakecast/app/util.py
shakecast/app/admin/__init__.py
shakecast/app/admin/templates.py
shakecast/app/linux/__init__.py
shakecast/app/linux/__main__.py
shakecast/app/linux/controls.py
shakecast/app/linux/server_service.py
shakecast/app/linux/web_server_service.py
shakecast/app/notifications/__init__.py
shakecast/app/notifications/builder.py
shakecast/app/notifications/mailer.py
shakecast/app/notifications/notifications.py
shakecast/app/notifications/templates.py
shakecast/app/orm/__init__.py
shakecast/app/orm/data.py
shakecast/app/orm/engine.py
shakecast/app/orm/migrations.py
shakecast/app/orm/objects.py
shakecast/app/orm/session.py
shakecast/app/orm/util.py
shakecast/app/orm/utils.py
shakecast/app/plugins/.keep
shakecast/app/plugins/__init__.py
shakecast/app/products/__init__.py
shakecast/app/products/geojson.py
shakecast/app/products/pdf.py
shakecast/app/products/sc_csv.py
shakecast/app/products/summary_csv.py
shakecast/app/products/geojsonhtml/__init__.py
shakecast/app/products/geojsonhtml/geojsonhtml.py
shakecast/app/products/geojsonhtml/template.html
shakecast/app/windows/__init__.py
shakecast/app/windows/__main__.py
shakecast/app/windows/controls.py
shakecast/app/windows/server_service.py
shakecast/app/windows/set_paths.py
shakecast/app/windows/web_server_service.py
shakecast/conf/sc.json
shakecast/templates/csv/default.json
shakecast/web_src/src/app/shakecast-admin/facilities/facility-info/facility-info.component.css
shakecast/web_src/src/app/shakecast-admin/facilities/facility-info/facility-info.component.html
shakecast/web_src/src/app/shakecast-admin/facilities/facility-info/facility-info.component.ts
usgs_shakecast-4.2.3.dist-info/LICENSE.md
usgs_shakecast-4.2.3.dist-info/METADATA
usgs_shakecast-4.2.3.dist-info/WHEEL
usgs_shakecast-4.2.3.dist-info/top_level.txt
usgs_shakecast-4.2.3.dist-info/RECORD
