Metadata-Version: 2.1
Name: usgs-shakecast
Version: 4.2.3
Summary: Real time facility monitoring and notifications for earthquake impacts
Home-page: https://github.com/usgs/shakecast
Author: Daniel Slosky
Author-email: dslosky@usgs.gov
License: MIT
Keywords: impact hazus aebm earthquake damage
Platform: UNKNOWN
Classifier: Development Status :: 3 - Alpha
Classifier: Intended Audience :: Science/Research
Classifier: Topic :: Scientific/Engineering
Classifier: License :: OSI Approved :: MIT License
Classifier: Programming Language :: Python :: 2.7
Classifier: Programming Language :: Python :: 3.6
Requires-Dist: Flask (==1.1.4)
Requires-Dist: markupsafe (==2.0.1)
Requires-Dist: Flask-Login (==0.4.1)
Requires-Dist: Flask-Uploads (==0.2.1)
Requires-Dist: fpdf (==1.7.2)
Requires-Dist: pylint (==1.9.4)
Requires-Dist: shakecast-aebm (==0.0a10)
Requires-Dist: SQLAlchemy (==1.3.24)
Requires-Dist: urllib3 (==1.24.3)
Requires-Dist: Werkzeug (==0.15.5)
Requires-Dist: xmltodict (==0.10.2)
Requires-Dist: sqlalchemy-utils (==0.36.8)
